nescree32/README.MD
nescree32/__init__.py
nescree32/requirements.txt
nescree32/thirdparty.json
nescree32-0.10.dist-info/LICENSE.rst
nescree32-0.10.dist-info/METADATA
nescree32-0.10.dist-info/WHEEL
nescree32-0.10.dist-info/top_level.txt
nescree32-0.10.dist-info/RECORD
