Metadata-Version: 2.1
Name: nescree32
Version: 0.10
Summary: Fast Bluestacks screenshots with pywin32
Home-page: https://github.com/hansalemaos/nescree32
Author: Johannes Fischer
Author-email: aulasparticularesdealemaosp@gmail.com
License: MIT
Keywords: utils,Bluestacks
Classifier: Development Status :: 4 - Beta
Classifier: Programming Language :: Python :: 3 :: Only
Classifier: Programming Language :: Python :: 3.10
Classifier: Topic :: Software Development :: Libraries :: Python Modules
Classifier: Topic :: Utilities
License-File: LICENSE.rst
Requires-Dist: getbstacksinfo
Requires-Dist: nodepsutils
Requires-Dist: numpy
Requires-Dist: pywin32
